pynance_api/__init__.py
pynance_api/app.py
pynance_calc-0.0.1.dist-info/METADATA
pynance_calc-0.0.1.dist-info/WHEEL
pynance_calc-0.0.1.dist-info/top_level.txt
pynance_calc-0.0.1.dist-info/RECORD
